README.rst
setup.py
PyGhostLid.egg-info/PKG-INFO
PyGhostLid.egg-info/SOURCES.txt
PyGhostLid.egg-info/dependency_links.txt
PyGhostLid.egg-info/top_level.txt
PyGhostLid.egg-info/zip-safe
ghostlid/__init__.py
ghostlid/ghostlid.py
test/test_ghostlid.py