Metadata-Version: 1.1
Name: PyGhostLid
Version: 0.2.0
Summary: Submit and retrieve pastes from GhostBin within your application! Supports both ghostbin.com and any self-hosted instances of ghostbin.
Home-page: https://github.com/Laogeodritt/pyghostlid
Author: Marc-Alexandre Chan
Author-email: laogeodritt@arenthil.net
License: Modified BSD
Download-URL: https://github.com/Laogeodritt/pyghostlid/tarball/0.2.0
Keywords: ghostbin,pastebin,api,upload
Platform: UNKNOWN
Classifier: Development Status :: 3 - Alpha
Classifier: License :: OSI Approved :: BSD License
Classifier: Topic :: Software Development :: Libraries :: Python Modules
